[
    {
        "id":1,
        "name":"UA Infinite Elite",
        "title":"Men/Shop By Sport/Running/Shoes/UA Infinite Elite",
        "price":"MRP ₹16,999",
        "category":"shoes",
        "image":"https://www.underarmour.in/media/catalog/product/cache/a6c9600f6d89dc76028bfa07e5e1eb9a/3/0/3027189-120240130204850153.jpg"
    },
    {
        "id":2,
        "name":"JAUNTZA SHOES",
        "title":"Men/Shop By Sport/Running/MenRunning",
        "price":"MRP ₹11,999",
        "category":"shoes",
        "image":"https://assets.adidas.com/images/h_840,f_auto,q_auto,fl_lossy,c_fill,g_auto/668a704b2e874cafadfaf92754adf63a_9366/JAUNTZA_SHOES_Blue_IQ9797_01_standard.jpg"
    },
    {
        "id":3,
        "name":"Casual Trainers",
        "title":"Men/Shop By Sport/Running/Shoes/UA Infinite Elite",
        "price":"MRP ₹1,999",
        "category":"shoes",
        "image":"https://neemans.com/cdn/shop/files/ND-CasualTrainers-NewIvory-_WebOptimized_d_1000x.jpg?v=1711690138"
    },
    {
        "id":4,
        "name":"HRX by Hrithik Roshan Men",
        "title":"Men/Shop By Sport/Running/Shoes/UA Infinite Elite",
        "price":"MRP ₹6,999",
        "category":"shoes",
        "image":"https://encrypted-tbn0.gstatic.com/shopping?q=tbn:ANd9GcT1dluE3Vacsmkq5uPoyw3t6SjMtFKbiitSl_00P1d0qcXCdafYkutd17P9UG_zm8kOQFruOI9HWV4o1JSFgGQ3m-cd5zKMoR8ONuItUkk"
    },
    {
        "id":5,
        "name":"UA Infinite Elite",
        "title":"Men/Shop By Sport/Running/Shoes/UA Infinite Elite",
        "price":"MRP ₹16,999",
        "category":"shoes",
        "image":"https://www.underarmour.in/media/catalog/product/cache/a6c9600f6d89dc76028bfa07e5e1eb9a/3/0/3027189-120240130204850153.jpg"
    },
    {
        "id":6,
        "name":"UA Infinite Elite",
        "title":"Men/Shop By Sport/Running/Shoes/UA Infinite Elite",
        "price":"MRP ₹16,999",
        "category":"shoes",
        "image":"https://www.underarmour.in/media/catalog/product/cache/a6c9600f6d89dc76028bfa07e5e1eb9a/3/0/3027189-120240130204850153.jpg"
    },
    {
        "id":7,
        "name":"UA Infinite Elite",
        "title":"Men/Shop By Sport/Running/Shoes/UA Infinite Elite",
        "price":"MRP ₹16,999",
        "category":"shoes",
        "image":"https://www.underarmour.in/media/catalog/product/cache/a6c9600f6d89dc76028bfa07e5e1eb9a/3/0/3027189-120240130204850153.jpg"
    },
    {
        "id":8,
        "name":"UA Infinite Elite",
        "title":"Men/Shop By Sport/Running/Shoes/UA Infinite Elite",
        "price":"MRP ₹16,999",
        "category":"shoes",
        "image":"https://www.underarmour.in/media/catalog/product/cache/a6c9600f6d89dc76028bfa07e5e1eb9a/3/0/3027189-120240130204850153.jpg"
    },
    {
        "id":9,
        "name":"UA Infinite Elite",
        "title":"Men/Shop By Sport/Running/Shoes/UA Infinite Elite",
        "price":"MRP ₹16,999",
        "category":"shoes",
        "image":"https://www.underarmour.in/media/catalog/product/cache/a6c9600f6d89dc76028bfa07e5e1eb9a/3/0/3027189-120240130204850153.jpg"
    },
    {
        "id":10,
        "name":"UA Infinite Elite",
        "title":"Men/Shop By Sport/Running/Shoes/UA Infinite Elite",
        "price":"MRP ₹16,999",
        "category":"shoes",
        "image":"https://www.underarmour.in/media/catalog/product/cache/a6c9600f6d89dc76028bfa07e5e1eb9a/3/0/3027189-120240130204850153.jpg"
    },
    {
        "id":11,
        "name":"UA Infinite Elite",
        "title":"Men/Shop By Sport/Running/Shoes/UA Infinite Elite",
        "price":"MRP ₹16,999",
        "category":"shoes",
        "image":"https://www.underarmour.in/media/catalog/product/cache/a6c9600f6d89dc76028bfa07e5e1eb9a/3/0/3027189-120240130204850153.jpg"
    },
    {
        "id":12,
        "name":"UA Infinite Elite",
        "title":"Men/Shop By Sport/Running/Shoes/UA Infinite Elite",
        "price":"MRP ₹16,999",
        "category":"shoes",
        "image":"https://www.underarmour.in/media/catalog/product/cache/a6c9600f6d89dc76028bfa07e5e1eb9a/3/0/3027189-120240130204850153.jpg"
    },
    {
        "id":13,
        "name":"UA Infinite Elite",
        "title":"Men/Shop By Sport/Running/Shoes/UA Infinite Elite",
        "price":"MRP ₹0",
        "category":"free",
        "image":"https://www.underarmour.in/media/catalog/product/cache/a6c9600f6d89dc76028bfa07e5e1eb9a/3/0/3027189-120240130204850153.jpg"
    },
    {
        "id":14,
        "name":"UA Infinite Elite",
        "title":"Men/Shop By Sport/Running/Shoes/UA Infinite Elite",
        "price":"MRP ₹0",
        "category":"free",
        "image":"https://www.underarmour.in/media/catalog/product/cache/a6c9600f6d89dc76028bfa07e5e1eb9a/3/0/3027189-120240130204850153.jpg"
    },
    {
        "id":15,
        "name":"UA Infinite Elite",
        "title":"Men/Shop By Sport/Running/Shoes/UA Infinite Elite",
        "price":"MRP ₹0",
        "category":"free",
        "image":"https://www.underarmour.in/media/catalog/product/cache/a6c9600f6d89dc76028bfa07e5e1eb9a/3/0/3027189-120240130204850153.jpg"
    },
    {
        "id":16,
        "name":"UA Infinite Elite",
        "title":"Men/Shop By Sport/Running/Shoes/UA Infinite Elite",
        "price":"MRP ₹0",
        "category":"free",
        "image":"https://www.underarmour.in/media/catalog/product/cache/a6c9600f6d89dc76028bfa07e5e1eb9a/3/0/3027189-120240130204850153.jpg"
    },
    {
        "id":17,
        "name":"UA Infinite Elite",
        "title":"Men/Shop By Sport/Running/Shoes/UA Infinite Elite",
        "price":"MRP ₹0",
        "category":"free",
        "image":"https://www.underarmour.in/media/catalog/product/cache/a6c9600f6d89dc76028bfa07e5e1eb9a/3/0/3027189-120240130204850153.jpg"
    },
    {
        "id":18,
        "name":"UA Infinite Elite",
        "title":"Men/Shop By Sport/Running/Shoes/UA Infinite Elite",
        "price":"MRP ₹0",
        "category":"free",
        "image":"https://www.underarmour.in/media/catalog/product/cache/a6c9600f6d89dc76028bfa07e5e1eb9a/3/0/3027189-120240130204850153.jpg"
    },
    {
        "id":19,
        "name":"UA Infinite Elite",
        "title":"Men/Shop By Sport/Running/Shoes/UA Infinite Elite",
        "price":"MRP ₹0",
        "category":"free",
        "image":"https://www.underarmour.in/media/catalog/product/cache/a6c9600f6d89dc76028bfa07e5e1eb9a/3/0/3027189-120240130204850153.jpg"
    },
    {
        "id":20,
        "name":"UA Infinite Elite",
        "title":"Men/Shop By Sport/Running/Shoes/UA Infinite Elite",
        "price":"MRP ₹0",
        "category":"free",
        "image":"https://www.underarmour.in/media/catalog/product/cache/a6c9600f6d89dc76028bfa07e5e1eb9a/3/0/3027189-120240130204850153.jpg"
    }
]